goodfire/__init__.py
goodfire/api/__init__.py
goodfire/api/chat/__init__.py
goodfire/api/chat/client.py
goodfire/api/chat/interfaces.py
goodfire/api/client.py
goodfire/api/constants.py
goodfire/api/exceptions.py
goodfire/api/features/__init__.py
goodfire/api/features/client.py
goodfire/api/features/interfaces.py
goodfire/api/utils.py
goodfire/controller/__init__.py
goodfire/controller/controller.py
goodfire/controller/interfaces.py
goodfire/exceptions.py
goodfire/features/__init__.py
goodfire/features/features.py
goodfire/features/interfaces.py
goodfire/py.typed
goodfire/utils/__init__.py
goodfire/utils/asyncio.py
goodfire/utils/logger.py
goodfire/variants/__init__.py
goodfire/variants/variants.py
goodfire-0.3.5.dist-info/LICENSE
goodfire-0.3.5.dist-info/METADATA
goodfire-0.3.5.dist-info/WHEEL
goodfire-0.3.5.dist-info/RECORD
