Metadata-Version: 2.1
Name: goodfire
Version: 0.3.5
Summary: Understand and steer your AI models
License: Apache-2.0
Author: Goodfire
Requires-Python: >=3.10,<4.0
Classifier: Intended Audience :: Developers
Classifier: License :: OSI Approved :: Apache Software License
Classifier: Operating System :: MacOS
Classifier: Operating System :: Microsoft :: Windows
Classifier: Operating System :: OS Independent
Classifier: Operating System :: POSIX
Classifier: Operating System :: POSIX :: Linux
Classifier: Programming Language :: Python :: 3
Classifier: Programming Language :: Python :: 3.10
Classifier: Programming Language :: Python :: 3.11
Classifier: Programming Language :: Python :: 3.12
Classifier: Programming Language :: Python :: 3.13
Classifier: Programming Language :: Python :: 3.8
Classifier: Programming Language :: Python :: 3.9
Classifier: Topic :: Software Development :: Libraries :: Python Modules
Classifier: Typing :: Typed
Requires-Dist: httpx (>=0.27.2,<0.28.0)
Requires-Dist: ipywidgets (>=8.1.5,<9.0.0)
Requires-Dist: numpy (>=1.26.4)
Requires-Dist: pydantic (>=2.9.2,<3.0.0)
Requires-Dist: scikit-learn (>=1.6.0,<2.0.0)
Requires-Dist: scipy (>=1.14.1,<2.0.0)
